topsis_vani_102303078/__init__.py
topsis_vani_102303078/topsis.py
topsis_vani_102303078-1.0.1.dist-info/LICENSE
topsis_vani_102303078-1.0.1.dist-info/METADATA
topsis_vani_102303078-1.0.1.dist-info/WHEEL
topsis_vani_102303078-1.0.1.dist-info/entry_points.txt
topsis_vani_102303078-1.0.1.dist-info/top_level.txt
topsis_vani_102303078-1.0.1.dist-info/RECORD
