Metadata-Version: 2.1
Name: topsis-vani-102303078
Version: 1.0.1
Summary: A Python package for TOPSIS (Technique for Order Preference by Similarity to Ideal Solution)
Home-page: https://github.com/vgalpha/Topsis-Vani-102303078
Author: Vani Goyal
Author-email: vgoyal_be23@thapar.edu
Project-URL: Bug Reports, https://github.com/vgalpha/Topsis-Vani-102303078/issues
Project-URL: Source, https://github.com/vgalpha/Topsis-Vani-102303078
Keywords: topsis mcdm decision-making multi-criteria optimization ranking
Classifier: Development Status :: 3 - Alpha
Classifier: Intended Audience :: Developers
Classifier: Intended Audience :: Education
Classifier: Intended Audience :: Science/Research
Classifier: Topic :: Scientific/Engineering
Classifier: Topic :: Scientific/Engineering :: Mathematics
Classifier: License :: OSI Approved :: MIT License
Classifier: Programming Language :: Python :: 3
Classifier: Programming Language :: Python :: 3.7
Classifier: Programming Language :: Python :: 3.8
Classifier: Programming Language :: Python :: 3.9
Classifier: Programming Language :: Python :: 3.10
Classifier: Programming Language :: Python :: 3.11
Classifier: Operating System :: OS Independent
Requires-Python: >=3.7
License-File: LICENSE
Requires-Dist: pandas>=1.0.0
Requires-Dist: numpy>=1.18.0
